client/__init__.py
client/client_c.py
client/client_main.py
client/client_start.py
client/decorators.py
client/descriptor.py
client/form.py
client/metaclasses.py
client/test.py
client/common/__init__.py
client/common/utils.py
client/common/variables.py
client/log/__init__.py
client/log/client_log_config.py
client/log/server_log_config.py
mess_client_eTcilopp-0.5.2.dist-info/METADATA
mess_client_eTcilopp-0.5.2.dist-info/WHEEL
mess_client_eTcilopp-0.5.2.dist-info/top_level.txt
mess_client_eTcilopp-0.5.2.dist-info/RECORD
